{
  "portfolio": "Portfólio",
  "description": "Todos os trabalhos abaixo tiveram o back-end e o front-end feitos por mim, a menos que indicado de outra forma",
  "techs": "Tecnologias usadas",
  "profileDesc": "Desenvolvedor Web Full Stack localizado em Salvador, Bahia - Brasil",
  "contact": "Contato",
  "jusbrasilTitle": "Jusbrasil",
  "jusbrasilDesc": "Fui parte da equipe de desenvolvimento do Jusbrasil, a maior startup jurídica do Brasil com uma pilha de tecnologias diversa e variada. Trabalho no back-end, infraestrutura, aplicações e front-end.",
  ...
  "newTranslationKey": "New Translation Value"
}
